road_data_scraper/__init__.py
road_data_scraper/main.py
road_data_scraper/report/__init__.py
road_data_scraper/report/report.py
road_data_scraper/report/road_data_report_template.ipynb
road_data_scraper/steps/__init__.py
road_data_scraper/steps/download.py
road_data_scraper/steps/file_handler.py
road_data_scraper/steps/metadata.py
road_data_scraper-0.0.20.dist-info/LICENSE
road_data_scraper-0.0.20.dist-info/METADATA
road_data_scraper-0.0.20.dist-info/WHEEL
road_data_scraper-0.0.20.dist-info/top_level.txt
road_data_scraper-0.0.20.dist-info/RECORD
