Metadata-Version: 2.1
Name: road-data-scraper
Version: 0.0.20
Summary: Scrapes and Cleans WebTRIS Traffic Flow API
Author: Dominic Bean
License: MIT
Platform: unix
Platform: linux
Platform: osx
Platform: cygwin
Platform: win32
Classifier: Programming Language :: Python :: 3
Classifier: Programming Language :: Python :: 3 :: Only
Classifier: Programming Language :: Python :: 3.6
Classifier: Programming Language :: Python :: 3.7
Classifier: Programming Language :: Python :: 3.8
Classifier: Programming Language :: Python :: 3.9
Requires-Python: >=3.7
License-File: LICENSE
Requires-Dist: requests (>=2.25.1)
Requires-Dist: pandas (>=1.3.3)
Requires-Dist: papermill (>=2.3.3)
Requires-Dist: jupyterlab (>=3.1.12)
Requires-Dist: panel (>=0.12.3)
Requires-Dist: plotly (>=5.1.0)
Requires-Dist: google-cloud-storage (>=1.43.0)
Provides-Extra: testing
Requires-Dist: flake8 (>=3.9.2) ; extra == 'testing'
